hackprank/PyHack.py
hackprank/TerminalHack.py
hackprank/__init__.py
hackprank/fakeTerminalHack.py
hackprank/hackWeb.py
hackprank/matrix.py
hackprank-0.5.1.dist-info/METADATA
hackprank-0.5.1.dist-info/WHEEL
hackprank-0.5.1.dist-info/top_level.txt
hackprank-0.5.1.dist-info/RECORD
