Metadata-Version: 2.1
Name: hackprank
Version: 0.5.1
Summary: A Python Package Full Of Fake Hacking Programs To Prank Your Friends
Author: Aarav Goel
Keywords: python,hack,prank,cool,pyhacks,pyhack,pranks,hackprank,hackpranks
Classifier: Development Status :: 1 - Planning
Classifier: Intended Audience :: Developers
Classifier: Programming Language :: Python :: 3
Classifier: Operating System :: Unix
Classifier: Operating System :: MacOS :: MacOS X
Classifier: Operating System :: Microsoft :: Windows
Requires-Dist: rich
Requires-Dist: flask
Requires-Dist: pyfiglet
Requires-Dist: colorama
